dizzle/__init__.py
dizzle/db.py
dizzle/excel.py
dizzle/fun.py
dizzle/geo.py
dizzle/io.py
dizzle/utils.py
dizzle-0.2.1.dist-info/COPYING
dizzle-0.2.1.dist-info/WHEEL
dizzle-0.2.1.dist-info/METADATA
dizzle-0.2.1.dist-info/RECORD
